[{"Khoi":"KHOI 10","Mon":"DIA 10","SBD":"55100384","Ten file":"55100384 - Nguyễn Anh Thư.jpg","Link":"https://drive.google.com/file/d/1WZEmI2lPpxA1Wm_uCbYanxUg5AHRKcMM/view?usp=drivesdk"},{"Khoi":"KHOI 10","Mon":"DIA 10","SBD":"55100468","Ten file":"55100468 - Nguyễn Ngọc Thảo Vy.jpg","Link":"https://drive.google.com/file/d/111zEj_3Jmvzkn0cLJ_6kpF7Gwdh9C6oy/view?usp=drivesdk"},{"Khoi":"KHOI 10","Mon":"DIA 10","SBD":"55100467","Ten file":"55100467 - Nguyễn Khánh Vy.jpg","Link":"https://drive.google.com/file/d/18CEqn2AimYL3VWI2gpLbZ9Hn4EMDEDTX/view?usp=drivesdk"},{"Khoi":"KHOI 10","Mon":"DIA 10","SBD":"55100477","Ten file":"55100477 - Nguyễn Hải Yến.jpg","Link":"https://drive.google.com/file/d/1B3Gm_hkGmsQh2TYQbJNajV9BfQGwYRN6/view?usp=drivesdk"},{"Khoi":"KHOI 10","Mon":"DIA 10","SBD":"55100440","Ten file":"55100440 - Đỗ Ngọc Cát Tường.jpg","Link":"https://drive.google.com/file/d/1F4tpZDQrS-0PQAAcwgMTnMVnQD4i2vFH/view?usp=drivesdk"},{"Khoi":"KHOI 10","Mon":"DIA 10","SBD":"55100452","Ten file":"55100452 - Phan Nguyễn Khánh Vân.jpg","Link":"https://drive.google.com/file/d/1FrDhVwsH6mBlHQD2znwxaftZD6xOMohV/view?usp=drivesdk"},{"Khoi":"KHOI 10","Mon":"DIA 10","SBD":"55100448","Ten file":"55100448 - Trang Đào Tú Uyên.jpg","Link":"https://drive.google.com/file/d/1Lwr_Y0xHupoQ9UHBZZoiIE4H_zGUb-Iv/view?usp=drivesdk"},{"Khoi":"KHOI 10","Mon":"DIA 10","SBD":"55100472","Ten file":"55100472 - Nguyễn Võ Như Ý.jpg","Link":"https://drive.google.com/file/d/1Mj5WnhINrzuc75uxOEF51oQoWwiNB2fQ/view?usp=drivesdk"},{"Khoi":"KHOI 10","Mon":"DIA 10","SBD":"55100460","Ten file":"55100460 - Huỳnh Đặng Thúy Vy.jpg","Link":"https://drive.google.com/file/d/1OSiY0mYU8dm5TtY7SjjxYDJHrXgjUmC-/view?usp=drivesdk"},{"Khoi":"KHOI 10","Mon":"DIA 10","SBD":"55100461","Ten file":"55100461 - Huỳnh Ngọc Khải Vy.jpg","Link":"https://drive.google.com/file/d/1U8_VisZ5EKPlHlRNj7kdFiUVN0l1EwSd/view?usp=drivesdk"},{"Khoi":"KHOI 10","Mon":"DIA 10","SBD":"55100454","Ten file":"55100454 - Trần Thanh Vân.jpg","Link":"https://drive.google.com/file/d/1W1cTKncoWi0ZmJBBiUCbJpeFdcgEsnwC/view?usp=drivesdk"},{"Khoi":"KHOI 10","Mon":"DIA 10","SBD":"55100457","Ten file":"55100457 - Từ Thiếu Vinh.jpg","Link":"https://drive.google.com/file/d/1Ydv1MSyHca6ifRpvMRsmS124xkU7HSrF/view?usp=drivesdk"},{"Khoi":"KHOI 10","Mon":"DIA 10","SBD":"55100456","Ten file":"55100456 - Vũ Hoàng Việt.jpg","Link":"https://drive.google.com/file/d/1YkE0xdDrmWV2NnYUEfCcAyrCwnM0nzuc/view?usp=drivesdk"},{"Khoi":"KHOI 10","Mon":"DIA 10","SBD":"55100470","Ten file":"55100470 - Vũ Kim Xuân.jpg","Link":"https://drive.google.com/file/d/1_43JMs4FUFn2Ag6cpIcmLaiTcD9aSbix/view?usp=drivesdk"},{"Khoi":"KHOI 10","Mon":"DIA 10","SBD":"55100458","Ten file":"55100458 - Bùi Phương Vy.jpg","Link":"https://drive.google.com/file/d/1e163sqAtItMpVnKjrqYsmoCcW53pD3XT/view?usp=drivesdk"},{"Khoi":"KHOI 10","Mon":"DIA 10","SBD":"55100464","Ten file":"55100464 - Lê Trần Khả Vy.jpg","Link":"https://drive.google.com/file/d/1eI9DCoAIirNsRnVO9WIFGHXY55Om1fDM/view?usp=drivesdk"},{"Khoi":"KHOI 10","Mon":"DIA 10","SBD":"55100469","Ten file":"55100469 - Trương Đỗ Khánh Vy.jpg","Link":"https://drive.google.com/file/d/1geKf_2rAdZKxre2cjgbLRRhkRQzEieLL/view?usp=drivesdk"},{"Khoi":"KHOI 10","Mon":"DIA 10","SBD":"55100445","Ten file":"55100445 - Trần Minh Uy.jpg","Link":"https://drive.google.com/file/d/1h6dzEN6c5R3uFPkRmax1JjHtHlIDTjU7/view?usp=drivesdk"},{"Khoi":"KHOI 10","Mon":"DIA 10","SBD":"55100463","Ten file":"55100463 - Huỳnh Trà Lam Vy.jpg","Link":"https://drive.google.com/file/d/1kMBL3WfsMhC3o7mRyVPCNFNjkwZfndvN/view?usp=drivesdk"},{"Khoi":"KHOI 10","Mon":"DIA 10","SBD":"55100450","Ten file":"55100450 - Võ Hồng Khôi Văn.jpg","Link":"https://drive.google.com/file/d/1rYPSMEK0Kt1RwhPtjP5dC5iDDt-oATWd/view?usp=drivesdk"},{"Khoi":"KHOI 10","Mon":"DIA 10","SBD":"55100476","Ten file":"55100476 - Đinh Hoàng Yến.jpg","Link":"https://drive.google.com/file/d/1x9X2lDWBc4MKla1DEhkI9AJ3IgX-AxBW/view?usp=drivesdk"},{"Khoi":"KHOI 10","Mon":"DIA 10","SBD":"55100444","Ten file":"55100444 - Nguyễn Ngọc Cát Tường.jpg","Link":"https://drive.google.com/file/d/1zCyj-J6O2RPWx58P3ZR2u_yW7og39DRu/view?usp=drivesdk"},{"Khoi":"KHOI 10","Mon":"DIA 10","SBD":"55100404","Ten file":"55100404 - Lê Ngọc Bích Trâm.jpg","Link":"https://drive.google.com/file/d/101N7ifjtrGmx8yOSvh8v_4Nh2mSOCGRQ/view?usp=drivesdk"},{"Khoi":"KHOI 10","Mon":"DIA 10","SBD":"55100402","Ten file":"55100402 - Nguyễn Thùy Trang.jpg","Link":"https://drive.google.com/file/d/10oXwf0rV2_Elt2xolWD9z3owLG2IGUsd/view?usp=drivesdk"},{"Khoi":"KHOI 10","Mon":"DIA 10","SBD":"55100432","Ten file":"55100432 - Lâm Gia Tuấn.jpg","Link":"https://drive.google.com/file/d/13dpe5Nfh9-XxzlmSfXrj21q7ctGH9pXH/view?usp=drivesdk"},{"Khoi":"KHOI 10","Mon":"DIA 10","SBD":"55100350","Ten file":"55100350 - Lê Hồng Thiên Thanh.jpg","Link":"https://drive.google.com/file/d/14YbAg2aGGqsWmkVn_M8-TJqmhisK7x1z/view?usp=drivesdk"},{"Khoi":"KHOI 10","Mon":"DIA 10","SBD":"55100383","Ten file":"55100383 - Mai Minh Thư.jpg","Link":"https://drive.google.com/file/d/14zMqldUredsF3A8oSVbgvIMB-rCOarzQ/view?usp=drivesdk"},{"Khoi":"KHOI 10","Mon":"DIA 10","SBD":"55100409","Ten file":"55100409 - Nguyễn Đức Trí.jpg","Link":"https://drive.google.com/file/d/16UFnNBXsoJafbBvF8O8i_bBo7nZozn_9/view?usp=drivesdk"},{"Khoi":"KHOI 10","Mon":"DIA 10","SBD":"55100390","Ten file":"55100390 - Trần Lương Thiên Thư.jpg","Link":"https://drive.google.com/file/d/17kciVsuPjQmwfW4uu-h1njUCteSNrxI3/view?usp=drivesdk"},{"Khoi":"KHOI 10","Mon":"DIA 10","SBD":"55100416","Ten file":"55100416 - Lê Minh Triết.jpg","Link":"https://drive.google.com/file/d/18UDRveCxhtHlqiokc2se1wk1HTBWPQ3P/view?usp=drivesdk"},{"Khoi":"KHOI 10","Mon":"DIA 10","SBD":"55100358","Ten file":"55100358 - Nguyễn Ngọc Như Thảo.jpg","Link":"https://drive.google.com/file/d/18dG9TVUc-rCL8G3q4WktXlDPFOjpZDpd/view?usp=drivesdk"},{"Khoi":"KHOI 10","Mon":"DIA 10","SBD":"55100388","Ten file":"55100388 - Nguyễn Minh Thư.jpg","Link":"https://drive.google.com/file/d/19Ukq9IX0pr8kaY6MpNtGpsuYPYjk8fBt/view?usp=drivesdk"},{"Khoi":"KHOI 10","Mon":"DIA 10","SBD":"55100400","Ten file":"55100400 - Nguyễn Phúc Toàn.jpg","Link":"https://drive.google.com/file/d/1GDuOfMdlcioNgOCX_BXgTv5uYBqHmuXw/view?usp=drivesdk"},{"Khoi":"KHOI 10","Mon":"DIA 10","SBD":"55100433","Ten file":"55100433 - Nguyễn Anh Tuấn.jpg","Link":"https://drive.google.com/file/d/1JL0z-ftL7yv0czIw9SLjLhTdxyKixiBN/view?usp=drivesdk"},{"Khoi":"KHOI 10","Mon":"DIA 10","SBD":"55100372","Ten file":"55100372 - Nguyễn Gia Thịnh.jpg","Link":"https://drive.google.com/file/d/1Og2Mij86lZwyD-ghE-WOQYzePAZQn5OS/view?usp=drivesdk"},{"Khoi":"KHOI 10","Mon":"DIA 10","SBD":"55100407","Ten file":"55100407 - Phan Ngọc Trân.jpg","Link":"https://drive.google.com/file/d/1QahTb31rciEHt5cdb4ZO9qJFRx_YrjNo/view?usp=drivesdk"},{"Khoi":"KHOI 10","Mon":"DIA 10","SBD":"55100387","Ten file":"55100387 - Nguyễn Minh Thư.jpg","Link":"https://drive.google.com/file/d/1WkT8RXgGTSibp2MkUkcXMRRg_ye_Uvw9/view?usp=drivesdk"},{"Khoi":"KHOI 10","Mon":"DIA 10","SBD":"55100437","Ten file":"55100437 - Trầm Thanh Tuyền.jpg","Link":"https://drive.google.com/file/d/1Wx9QHU5yFREDwavMfSJh-v5RUJfHZbM6/view?usp=drivesdk"},{"Khoi":"KHOI 10","Mon":"DIA 10","SBD":"55100403","Ten file":"55100403 - Tống Lê Phương Trang.jpg","Link":"https://drive.google.com/file/d/1XMMMTHt5MP-4jXY5Q6yBMDSiKJjuDWPf/view?usp=drivesdk"},{"Khoi":"KHOI 10","Mon":"DIA 10","SBD":"55100417","Ten file":"55100417 - Lý Quang Triết.jpg","Link":"https://drive.google.com/file/d/1XbGnkQXD3_cZT96XghycaGpXC6btktqx/view?usp=drivesdk"},{"Khoi":"KHOI 10","Mon":"DIA 10","SBD":"55100363","Ten file":"55100363 - Nguyễn Hữu Thắng.jpg","Link":"https://drive.google.com/file/d/1Xl4qB4mqVHmxIeYn338lYrOuDNSUNjQi/view?usp=drivesdk"},{"Khoi":"KHOI 10","Mon":"DIA 10","SBD":"55100361","Ten file":"55100361 - Thái Phương Thảo.jpg","Link":"https://drive.google.com/file/d/1bQW3eWPADYGxkozrFo6nfK5IsRK-LDsL/view?usp=drivesdk"},{"Khoi":"KHOI 10","Mon":"DIA 10","SBD":"55100425","Ten file":"55100425 - Ngô Huỳnh Bảo Trúc.jpg","Link":"https://drive.google.com/file/d/1gxh9BV_N15QU0JDpPCaOmRZEegD3NWKe/view?usp=drivesdk"},{"Khoi":"KHOI 10","Mon":"DIA 10","SBD":"55100382","Ten file":"55100382 - Mai Anh Thư.jpg","Link":"https://drive.google.com/file/d/1mSkUBKb3L5w0doErYl5no1UQEm3UhBJr/view?usp=drivesdk"},{"Khoi":"KHOI 10","Mon":"DIA 10","SBD":"55100391","Ten file":"55100391 - Nguyễn Hà Khánh Thy.jpg","Link":"https://drive.google.com/file/d/1nlcumTvUPlSC_XOK7mtjIsPSlMMFYJ7z/view?usp=drivesdk"},{"Khoi":"KHOI 10","Mon":"DIA 10","SBD":"55100429","Ten file":"55100429 - Trần Xuân Trường.jpg","Link":"https://drive.google.com/file/d/1ooJxNCNEQNXjv327stCp_-YFYyUFdt1_/view?usp=drivesdk"},{"Khoi":"KHOI 10","Mon":"DIA 10","SBD":"55100431","Ten file":"55100431 - Võ Tú Tú.jpg","Link":"https://drive.google.com/file/d/1pq6Xjg33tW7NZAt1fkAl6xscC_YRNC1q/view?usp=drivesdk"},{"Khoi":"KHOI 10","Mon":"DIA 10","SBD":"55100362","Ten file":"55100362 - Dương Hồng Thắm.jpg","Link":"https://drive.google.com/file/d/1qHrnXw-W5tHQnvOHWYZFfNiTsr4FtQU1/view?usp=drivesdk"},{"Khoi":"KHOI 10","Mon":"DIA 10","SBD":"55100438","Ten file":"55100438 - Trần Thị Ngọc Tuyền.jpg","Link":"https://drive.google.com/file/d/1r8ZgpSgdFWnlluvJp26VNC7ww67-iRq_/view?usp=drivesdk"},{"Khoi":"KHOI 10","Mon":"DIA 10","SBD":"55100352","Ten file":"55100352 - Nguyễn Võ Đan Thanh.jpg","Link":"https://drive.google.com/file/d/1u-VSs9VJLixonky3ryND2acj739ly1QU/view?usp=drivesdk"},{"Khoi":"KHOI 10","Mon":"DIA 10","SBD":"55100370","Ten file":"55100370 - Lê Thiên Thịnh.jpg","Link":"https://drive.google.com/file/d/1u0kN8y9vokwXipM1GgaTodLODhvVFCie/view?usp=drivesdk"},{"Khoi":"KHOI 10","Mon":"DIA 10","SBD":"55100356","Ten file":"55100356 - Khưu Huỳnh Như Thảo.jpg","Link":"https://drive.google.com/file/d/1vRppSFvwPT6xHcaP4x20FL1jJdQGhhFs/view?usp=drivesdk"},{"Khoi":"KHOI 10","Mon":"DIA 10","SBD":"55100376","Ten file":"55100376 - Nguyễn Trí Thông.jpg","Link":"https://drive.google.com/file/d/1wz0yjQAQIOLNi3C4Arbto5d0bAXo7rkS/view?usp=drivesdk"},{"Khoi":"KHOI 10","Mon":"DIA 10","SBD":"55100314","Ten file":"55100314 - Nguyễn Hà Nam Phương.jpg","Link":"https://drive.google.com/file/d/10_PTWAB929TvpEabY2v9_GTH0-Mozsa4/view?usp=drivesdk"},{"Khoi":"KHOI 10","Mon":"DIA 10","SBD":"55100341","Ten file":"55100341 - Phạm Hoàng Sơn.jpg","Link":"https://drive.google.com/file/d/12r7wOiBn9ymsYKD9jFJuIhV9oISQK8DJ/view?usp=drivesdk"},{"Khoi":"KHOI 10","Mon":"DIA 10","SBD":"55100303","Ten file":"55100303 - Lê Trần Diệu Phúc.jpg","Link":"https://drive.google.com/file/d/14A7F6AVjFrr1y33uPTsCjwS9yCGsxTlT/view?usp=drivesdk"},{"Khoi":"KHOI 10","Mon":"DIA 10","SBD":"55100286","Ten file":"55100286 - Trần Thư Quỳnh Nhi.jpg","Link":"https://drive.google.com/file/d/16p1m29GRoGHTh9BrNO42z9uFZ6hHrkdk/view?usp=drivesdk"},{"Khoi":"KHOI 10","Mon":"DIA 10","SBD":"55100327","Ten file":"55100327 - Nguyễn Anh Quốc.jpg","Link":"https://drive.google.com/file/d/19BKUg3BZL1Hy7gos0i36bOPrlNRb1XFr/view?usp=drivesdk"},{"Khoi":"KHOI 10","Mon":"DIA 10","SBD":"55100304","Ten file":"55100304 - Mai Thành Phúc.jpg","Link":"https://drive.google.com/file/d/1DopeigmV3ANzjltu4_uO2xercNjT3qXo/view?usp=drivesdk"},{"Khoi":"KHOI 10","Mon":"DIA 10","SBD":"55100307","Ten file":"55100307 - Nguyễn Thiên Phúc.jpg","Link":"https://drive.google.com/file/d/1FxRR-Tj_X4ytq_FoxOWwOzFEkr-x8UST/view?usp=drivesdk"},{"Khoi":"KHOI 10","Mon":"DIA 10","SBD":"55100335","Ten file":"55100335 - Lâm Trúc Quỳnh.jpg","Link":"https://drive.google.com/file/d/1JRaCPrM9lp0JTzQ9Sd0x66jgsUOKZa7Y/view?usp=drivesdk"},{"Khoi":"KHOI 10","Mon":"DIA 10","SBD":"55100345","Ten file":"55100345 - Nguyễn Ngọc Mỹ Tâm.jpg","Link":"https://drive.google.com/file/d/1OskSFtCnmzzvLGUoXfjfsFeipAMO9B5d/view?usp=drivesdk"},{"Khoi":"KHOI 10","Mon":"DIA 10","SBD":"55100342","Ten file":"55100342 - Chung Văn Tài.jpg","Link":"https://drive.google.com/file/d/1QnJ61Ywm2zilfSnrXRzPdPvwoe-phcsr/view?usp=drivesdk"},{"Khoi":"KHOI 10","Mon":"DIA 10","SBD":"55100318","Ten file":"55100318 - Thái Dương Trúc Phương.jpg","Link":"https://drive.google.com/file/d/1R0_SdSB0BCSO3VcYvGgdWZxuVlir7tMZ/view?usp=drivesdk"},{"Khoi":"KHOI 10","Mon":"DIA 10","SBD":"55100339","Ten file":"55100339 - Võ Ngọc Như Quỳnh.jpg","Link":"https://drive.google.com/file/d/1S7lctc1oxDs3HUupIsbZbDNLyu92ZZ_v/view?usp=drivesdk"},{"Khoi":"KHOI 10","Mon":"DIA 10","SBD":"55100334","Ten file":"55100334 - Đoàn Nguyễn Thúy Quỳnh.jpg","Link":"https://drive.google.com/file/d/1U-4VYfzqEkqfjCM7FkkuhQmwumqIyHaq/view?usp=drivesdk"},{"Khoi":"KHOI 10","Mon":"DIA 10","SBD":"55100344","Ten file":"55100344 - Lê Ngọc Minh Tâm.jpg","Link":"https://drive.google.com/file/d/1WjrAaFAVIU51hUog6gpLw1ONKd8_e9-G/view?usp=drivesdk"},{"Khoi":"KHOI 10","Mon":"DIA 10","SBD":"55100348","Ten file":"55100348 - Đỗ Hoàng Thiên Thanh.jpg","Link":"https://drive.google.com/file/d/1XoZ2slelPdIkKAFOOmrebW3-CSAgKI9Y/view?usp=drivesdk"},{"Khoi":"KHOI 10","Mon":"DIA 10","SBD":"55100321","Ten file":"55100321 - Nguyễn Nhựt Quang.jpg","Link":"https://drive.google.com/file/d/1YJnFtlVG8-IcFtDmr4XlymFTCJk14hHF/view?usp=drivesdk"},{"Khoi":"KHOI 10","Mon":"DIA 10","SBD":"55100284","Ten file":"55100284 - Lê Nguyễn Thảo Nhi.jpg","Link":"https://drive.google.com/file/d/1_ryJzVaaHg-YSEW42SzTn3QrQQDNJwTC/view?usp=drivesdk"},{"Khoi":"KHOI 10","Mon":"DIA 10","SBD":"55100298","Ten file":"55100298 - Huỳnh Gia Phú.jpg","Link":"https://drive.google.com/file/d/1bq4_xL-kkyaKnGlqjFhwWI7BGc3MdEjn/view?usp=drivesdk"},{"Khoi":"KHOI 10","Mon":"DIA 10","SBD":"55100319","Ten file":"55100319 - Trần Mai Phương.jpg","Link":"https://drive.google.com/file/d/1diljn2-B6J_z0kT-m0wk1RK3hqO-myqq/view?usp=drivesdk"},{"Khoi":"KHOI 10","Mon":"DIA 10","SBD":"55100300","Ten file":"55100300 - Phạm Minh Phú.jpg","Link":"https://drive.google.com/file/d/1j1vhkFjP9ON4mvF-r69m9mXXGWgiZlA5/view?usp=drivesdk"},{"Khoi":"KHOI 10","Mon":"DIA 10","SBD":"55100297","Ten file":"55100297 - Lê Trần Thuận Phát.jpg","Link":"https://drive.google.com/file/d/1jh_ulJYPvEmmPodD07XiB0yNEqSCGpTq/view?usp=drivesdk"},{"Khoi":"KHOI 10","Mon":"DIA 10","SBD":"55100316","Ten file":"55100316 - Phạm Lan Phương.jpg","Link":"https://drive.google.com/file/d/1lvaSe9n6qLqP_WTrItHA5NcxpGbnrdu_/view?usp=drivesdk"},{"Khoi":"KHOI 10","Mon":"DIA 10","SBD":"55100289","Ten file":"55100289 - Nguyễn Ngọc Khánh Nhu.jpg","Link":"https://drive.google.com/file/d/1mNgkSz3l6tO5-n8OnknDIpxZEwEWpmJs/view?usp=drivesdk"},{"Khoi":"KHOI 10","Mon":"DIA 10","SBD":"55100331","Ten file":"55100331 - Trần Lê Đỗ Quyên.jpg","Link":"https://drive.google.com/file/d/1r6cnjZ9m6JmYrZx4bGkxKTkRhkfQTIJp/view?usp=drivesdk"},{"Khoi":"KHOI 10","Mon":"DIA 10","SBD":"55100320","Ten file":"55100320 - Hứa Kiến Quang.jpg","Link":"https://drive.google.com/file/d/1swJ2owduvUjaGshArJjqLvlzbBHc-O1V/view?usp=drivesdk"},{"Khoi":"KHOI 10","Mon":"DIA 10","SBD":"55100291","Ten file":"55100291 - Lê Quỳnh Như.jpg","Link":"https://drive.google.com/file/d/1tIg6vIjIpzatLEH2AaceVQTcj4z3aJ6g/view?usp=drivesdk"},{"Khoi":"KHOI 10","Mon":"DIA 10","SBD":"55100306","Ten file":"55100306 - Nguyễn Phan Gia Phúc.jpg","Link":"https://drive.google.com/file/d/1td-ezjLUTTFYkqNHQuZvn3av48QN68Qn/view?usp=drivesdk"},{"Khoi":"KHOI 10","Mon":"DIA 10","SBD":"55100349","Ten file":"55100349 - Đỗ Phạm Lan Thanh.jpg","Link":"https://drive.google.com/file/d/1w_2Rit50zSM9j2j7jvWY1qXT2yMPazbs/view?usp=drivesdk"},{"Khoi":"KHOI 10","Mon":"DIA 10","SBD":"55100292","Ten file":"55100292 - Nguyễn Ngọc Tố Như.jpg","Link":"https://drive.google.com/file/d/1xS8GXcTVPcBpnajT0_cllgVSZ6slOqmh/view?usp=drivesdk"},{"Khoi":"KHOI 10","Mon":"DIA 10","SBD":"55100288","Ten file":"55100288 - Nguyễn Thái Kỳ Nhiên.jpg","Link":"https://drive.google.com/file/d/1xeDAGYfsBdmC0zijcbDBD7Se1FZ1uliC/view?usp=drivesdk"},{"Khoi":"KHOI 10","Mon":"DIA 10","SBD":"55100276","Ten file":"55100276 - Cao Thiện Nhân.jpg","Link":"https://drive.google.com/file/d/16_5gawtpXcPZFs7g33SnsslXcBJttuAt/view?usp=drivesdk"},{"Khoi":"KHOI 10","Mon":"DIA 10","SBD":"55100239","Ten file":"55100239 - Trần Ngọc Khánh Ngân.jpg","Link":"https://drive.google.com/file/d/1QjpEh5sYxehwzBdKsVBtB0exGXBvSfGx/view?usp=drivesdk"},{"Khoi":"KHOI 10","Mon":"DIA 10","SBD":"55100207","Ten file":"55100207 - Huỳnh Ngọc Mai.jpg","Link":"https://drive.google.com/file/d/1RbIEqgT7c1Qn723mo5Z9CWw4Sbf9ghes/view?usp=drivesdk"},{"Khoi":"KHOI 10","Mon":"DIA 10","SBD":"55100215","Ten file":"55100215 - Nguyễn Xuân Minh.jpg","Link":"https://drive.google.com/file/d/1RfI2wXZPsjNjub3APiAyMzKPfiAQZttR/view?usp=drivesdk"},{"Khoi":"KHOI 10","Mon":"DIA 10","SBD":"55100243","Ten file":"55100243 - Nguyễn Tấn Nghi.jpg","Link":"https://drive.google.com/file/d/1SeGGSBEkCMiNjxHJEu5FzTDZuLxhoHej/view?usp=drivesdk"},{"Khoi":"KHOI 10","Mon":"DIA 10","SBD":"55100277","Ten file":"55100277 - Giang Hoàng Nhân.jpg","Link":"https://drive.google.com/file/d/1T8jaCglxWBKXDbUoYVb2lGD33-HtIVJO/view?usp=drivesdk"},{"Khoi":"KHOI 10","Mon":"DIA 10","SBD":"55100270","Ten file":"55100270 - Ngô Dương Thảo Nguyên.jpg","Link":"https://drive.google.com/file/d/1U6QV1U7-gl_wo4DzvQPGOUGt5l8AwrM9/view?usp=drivesdk"},{"Khoi":"KHOI 10","Mon":"DIA 10","SBD":"55100232","Ten file":"55100232 - Lê Thảo Ngân.jpg","Link":"https://drive.google.com/file/d/1Z4QGmDe10JjVUMqWUtJfCIyT069IlMzA/view?usp=drivesdk"},{"Khoi":"KHOI 10","Mon":"DIA 10","SBD":"55100212","Ten file":"55100212 - Đoàn Ngọc Minh.jpg","Link":"https://drive.google.com/file/d/1au4KjFyqOY35B6XH2fvPDaHbZ9AT0pz-/view?usp=drivesdk"},{"Khoi":"KHOI 10","Mon":"DIA 10","SBD":"55100248","Ten file":"55100248 - Đoàn Minh Khánh Ngọc.jpg","Link":"https://drive.google.com/file/d/1cNlnKsc2fkUTqbHVH8MAUJ0QpJWlDTk5/view?usp=drivesdk"},{"Khoi":"KHOI 10","Mon":"DIA 10","SBD":"55100240","Ten file":"55100240 - Đinh Nhật Nghi.jpg","Link":"https://drive.google.com/file/d/1hTTrcSTOJ499dT6ZQ2mbJvfU9RJPYN2y/view?usp=drivesdk"},{"Khoi":"KHOI 10","Mon":"DIA 10","SBD":"55100252","Ten file":"55100252 - Lê Nguyễn Khánh Ngọc.jpg","Link":"https://drive.google.com/file/d/1k6mjYOWULqgfqrk-rWy5I_Vaiecveung/view?usp=drivesdk"},{"Khoi":"KHOI 10","Mon":"DIA 10","SBD":"55100256","Ten file":"55100256 - Nguyễn Bảo Ngọc.jpg","Link":"https://drive.google.com/file/d/1lnh-m3sT7YeLfXV4sJM6GuzZgDIkzQxH/view?usp=drivesdk"},{"Khoi":"KHOI 10","Mon":"DIA 10","SBD":"55100219","Ten file":"55100219 - Trương Tiến Minh.jpg","Link":"https://drive.google.com/file/d/1m7ChY_nisIVPkrpsT2jG3yAcK7thRldO/view?usp=drivesdk"},{"Khoi":"KHOI 10","Mon":"DIA 10","SBD":"55100268","Ten file":"55100268 - Lê Vĩnh Nguyên.jpg","Link":"https://drive.google.com/file/d/1rU0jlYpfcJW1Ig1wbLCVu5p2UQJl0iY5/view?usp=drivesdk"},{"Khoi":"KHOI 10","Mon":"DIA 10","SBD":"55100260","Ten file":"55100260 - Nguyễn Khánh Ngọc.jpg","Link":"https://drive.google.com/file/d/1sc8Wo9awgkautcLDEu-UAC7zxcGwmdgp/view?usp=drivesdk"},{"Khoi":"KHOI 10","Mon":"DIA 10","SBD":"55100204","Ten file":"55100204 - Lê Thiên Lộc.jpg","Link":"https://drive.google.com/file/d/1xJedwus0VSITjrquxNO4qRZIbb1T0fju/view?usp=drivesdk"},{"Khoi":"KHOI 10","Mon":"DIA 10","SBD":"55100269","Ten file":"55100269 - Mai Phúc Nguyên.jpg","Link":"https://drive.google.com/file/d/1-YgnFCgM8KXuNhmm6bBmem0GyU9rN-Pu/view?usp=drivesdk"},{"Khoi":"KHOI 10","Mon":"DIA 10","SBD":"55100226","Ten file":"55100226 - Trần Hoàng Nam.jpg","Link":"https://drive.google.com/file/d/1AEFz40sEEDdlXMOFbqZlsUK0QrbMn6Ep/view?usp=drivesdk"},{"Khoi":"KHOI 10","Mon":"DIA 10","SBD":"55100222","Ten file":"55100222 - Lý Lê Nam.jpg","Link":"https://drive.google.com/file/d/1HYsG2kMo9mepH2Vj1pCnf3Sm9jU_DPgS/view?usp=drivesdk"},{"Khoi":"KHOI 10","Mon":"DIA 10","SBD":"55100245","Ten file":"55100245 - Trần Thụy Tường Nghi.jpg","Link":"https://drive.google.com/file/d/1M66X-8Cpw-JH2IkROxdbuX12hZ7m0tIZ/view?usp=drivesdk"},{"Khoi":"KHOI 10","Mon":"DIA 10","SBD":"55100262","Ten file":"55100262 - Nguyễn Trần Khánh Ngọc.jpg","Link":"https://drive.google.com/file/d/1MT7DGrb_0tyiLj-AytCe5VQxOvmkFIh-/view?usp=drivesdk"},{"Khoi":"KHOI 10","Mon":"DIA 10","SBD":"55100282","Ten file":"55100282 - Hồ Thiên Nhi.jpg","Link":"https://drive.google.com/file/d/1N_g0kdrqsgcPzcopAZS_wWDx7IZrpJvA/view?usp=drivesdk"},{"Khoi":"KHOI 10","Mon":"DIA 10","SBD":"55100230","Ten file":"55100230 - Huỳnh Ngọc Yến Ngân.jpg","Link":"https://drive.google.com/file/d/1Se2CPUcTQcAiQ-mILFm2_A09WN-wEZIb/view?usp=drivesdk"},{"Khoi":"KHOI 10","Mon":"DIA 10","SBD":"55100236","Ten file":"55100236 - Nguyễn Trần Kim Ngân.jpg","Link":"https://drive.google.com/file/d/1VPenhxA54tvlf0gU1x3jnUie2tJvfKLi/view?usp=drivesdk"},{"Khoi":"KHOI 10","Mon":"DIA 10","SBD":"55100263","Ten file":"55100263 - Phạm Nguyễn Bảo Ngọc.jpg","Link":"https://drive.google.com/file/d/1e2NbDt7sADP1v2NWu2bcO-QqBOVn-YKm/view?usp=drivesdk"},{"Khoi":"KHOI 10","Mon":"DIA 10","SBD":"55100227","Ten file":"55100227 - Trần Khoa Nam.jpg","Link":"https://drive.google.com/file/d/1gh6kt1NsTMrgervi4i45m2VMOS0Yxv5o/view?usp=drivesdk"},{"Khoi":"KHOI 10","Mon":"DIA 10","SBD":"55100234","Ten file":"55100234 - Nguyễn Ngọc Kim Ngân.jpg","Link":"https://drive.google.com/file/d/1kulxsVlQlZ596LHrdIjqwcRrVGtZhths/view?usp=drivesdk"},{"Khoi":"KHOI 10","Mon":"DIA 10","SBD":"55100246","Ten file":"55100246 - Nguyễn Trung Nghĩa.jpg","Link":"https://drive.google.com/file/d/1oJvVCwAoTIi5ggkEDmRhYDgfIxFd_czg/view?usp=drivesdk"},{"Khoi":"KHOI 10","Mon":"DIA 10","SBD":"55100261","Ten file":"55100261 - Nguyễn Lê Khánh Ngọc.jpg","Link":"https://drive.google.com/file/d/1oXgrJRTz0I1g3CUcICbbxwIIzxt9gUoO/view?usp=drivesdk"},{"Khoi":"KHOI 10","Mon":"DIA 10","SBD":"55100267","Ten file":"55100267 - Lê Kim Nguyên.jpg","Link":"https://drive.google.com/file/d/1sWuXn-1RlMPokr6weDGoTyJd1wFIpaQi/view?usp=drivesdk"},{"Khoi":"KHOI 10","Mon":"DIA 10","SBD":"55100237","Ten file":"55100237 - Trần Hoàng Ngân.jpg","Link":"https://drive.google.com/file/d/1uYFyevTGzRQYi_vtzI1DmcgbIqFP2qfh/view?usp=drivesdk"},{"Khoi":"KHOI 10","Mon":"DIA 10","SBD":"55100253","Ten file":"55100253 - Lê Phương Bảo Ngọc.jpg","Link":"https://drive.google.com/file/d/1xYF2ExZwnNhHEYwRfkuzEWhAhDoW6b-r/view?usp=drivesdk"},{"Khoi":"KHOI 10","Mon":"DIA 10","SBD":"55100274","Ten file":"55100274 - Trần Võ Phương Nguyên.jpg","Link":"https://drive.google.com/file/d/1yjOI0b9r-zDS8ZWIpidbuToqc1Zf4RVe/view?usp=drivesdk"},{"Khoi":"KHOI 10","Mon":"DIA 10","SBD":"55100132","Ten file":"55100132 - Trần Ngô Huy Hoàng.jpg","Link":"https://drive.google.com/file/d/10oIkRm8JYga_MRiZnYLTDDC3Bfpwoccl/view?usp=drivesdk"},{"Khoi":"KHOI 10","Mon":"DIA 10","SBD":"55100113","Ten file":"55100113 - Trần Vỹ Hào.jpg","Link":"https://drive.google.com/file/d/120lOAjQot6aKWZlPeayByFx-ygll4s46/view?usp=drivesdk"},{"Khoi":"KHOI 10","Mon":"DIA 10","SBD":"55100126","Ten file":"55100126 - Nguyễn Trọng Hiếu.jpg","Link":"https://drive.google.com/file/d/127g62Hlo6vD4LKtznWUtD2lDKdeHgyz8/view?usp=drivesdk"},{"Khoi":"KHOI 10","Mon":"DIA 10","SBD":"55100119","Ten file":"55100119 - Nguyễn Ngọc Gia Hân.jpg","Link":"https://drive.google.com/file/d/15giBoA5_4MVmRvrtrHpo-gEbwyBkGyw4/view?usp=drivesdk"},{"Khoi":"KHOI 10","Mon":"DIA 10","SBD":"55100170","Ten file":"55100170 - Lê Đăng Khoa.jpg","Link":"https://drive.google.com/file/d/16PdpgvGp4F7ISKH9-zYazTB4XKSIezMk/view?usp=drivesdk"},{"Khoi":"KHOI 10","Mon":"DIA 10","SBD":"55100152","Ten file":"55100152 - Lâm Gia Khang.jpg","Link":"https://drive.google.com/file/d/19kqzcVm3JgTISRqZ2OK1XNLv7lc2Gi5E/view?usp=drivesdk"},{"Khoi":"KHOI 10","Mon":"DIA 10","SBD":"55100176","Ten file":"55100176 - Huỳnh Đăng Khôi.jpg","Link":"https://drive.google.com/file/d/1A9YJkGp_YvR8NX5cHEOolVw1LHuqm9fC/view?usp=drivesdk"},{"Khoi":"KHOI 10","Mon":"DIA 10","SBD":"55100197","Ten file":"55100197 - Võ Nguyệt Khiết Lâm.jpg","Link":"https://drive.google.com/file/d/1B2klhWVwwSAkBRIfvB39c6zVqafsJjRt/view?usp=drivesdk"},{"Khoi":"KHOI 10","Mon":"DIA 10","SBD":"55100088","Ten file":"55100088 - Đinh Ánh Dương.jpg","Link":"https://drive.google.com/file/d/1BQvtbFNy7bpFy5b5O-8gWR-OuSMzmo4M/view?usp=drivesdk"},{"Khoi":"KHOI 10","Mon":"DIA 10","SBD":"55100123","Ten file":"55100123 - Doãn Minh Hiếu.jpg","Link":"https://drive.google.com/file/d/1EeKfToN_qrUdNicRLjdDl8EIcqq8Od3O/view?usp=drivesdk"},{"Khoi":"KHOI 10","Mon":"DIA 10","SBD":"55100165","Ten file":"55100165 - Nguyễn Lê Ngân Khánh.jpg","Link":"https://drive.google.com/file/d/1EiuaPGR3IE3YiyQ82hj09D3-7vmzxIEG/view?usp=drivesdk"},{"Khoi":"KHOI 10","Mon":"DIA 10","SBD":"55100142","Ten file":"55100142 - Trần Đức Nhật Huy.jpg","Link":"https://drive.google.com/file/d/1F6uIPz4vh4xNm08DctFw2bzWSt4lRwIK/view?usp=drivesdk"},{"Khoi":"KHOI 10","Mon":"DIA 10","SBD":"55100096","Ten file":"55100096 - Lê Khánh Đoan.jpg","Link":"https://drive.google.com/file/d/1F7cQskmLlweUUizTPns2ENabf5kqrM_S/view?usp=drivesdk"},{"Khoi":"KHOI 10","Mon":"DIA 10","SBD":"55100167","Ten file":"55100167 - Trần Nam Khánh.jpg","Link":"https://drive.google.com/file/d/1GX2x-cs5hpoRBYQ1GcAJYU2Nx0QEZPLg/view?usp=drivesdk"},{"Khoi":"KHOI 10","Mon":"DIA 10","SBD":"55100181","Ten file":"55100181 - Võ Hoàng Khôi.jpg","Link":"https://drive.google.com/file/d/1H6THcB7nihmxbEPKN0bgtXVGobRbjy1x/view?usp=drivesdk"},{"Khoi":"KHOI 10","Mon":"DIA 10","SBD":"55100110","Ten file":"55100110 - Nguyễn Mỹ Hạnh.jpg","Link":"https://drive.google.com/file/d/1HpRXGUzb1WFtiC2mjaMGLu40Rm_Y_4Y1/view?usp=drivesdk"},{"Khoi":"KHOI 10","Mon":"DIA 10","SBD":"55100128","Ten file":"55100128 - Phan Trung Hiếu.jpg","Link":"https://drive.google.com/file/d/1KQh8tluv5PzQmkmVgadCFn0CNPROuvXx/view?usp=drivesdk"},{"Khoi":"KHOI 10","Mon":"DIA 10","SBD":"55100109","Ten file":"55100109 - Lê Phương Hạnh.jpg","Link":"https://drive.google.com/file/d/1LHDpGpELztVBXfiDKxuXkoFFHJTdRULF/view?usp=drivesdk"},{"Khoi":"KHOI 10","Mon":"DIA 10","SBD":"55100097","Ten file":"55100097 - Trần Hoàng Đô.jpg","Link":"https://drive.google.com/file/d/1P3s7nyyCoz0zl-m5eSjTDPPVV_w2sSLm/view?usp=drivesdk"},{"Khoi":"KHOI 10","Mon":"DIA 10","SBD":"55100116","Ten file":"55100116 - Khưu Gia Hân.jpg","Link":"https://drive.google.com/file/d/1PGxsGy3EFSUaw8cJIva5pTOWkgooLW_8/view?usp=drivesdk"},{"Khoi":"KHOI 10","Mon":"DIA 10","SBD":"55100185","Ten file":"55100185 - Nguyễn Hoàng Kim.jpg","Link":"https://drive.google.com/file/d/1QFjB409kfExzDMqT4hfZ6PxCrjd87d_y/view?usp=drivesdk"},{"Khoi":"KHOI 10","Mon":"DIA 10","SBD":"55100200","Ten file":"55100200 - Huỳnh Khánh Linh.jpg","Link":"https://drive.google.com/file/d/1SY92kPbxVwsk28qMXib-gOzAoS8BO-uZ/view?usp=drivesdk"},{"Khoi":"KHOI 10","Mon":"DIA 10","SBD":"55100144","Ten file":"55100144 - Nguyễn Thúy Huỳnh.jpg","Link":"https://drive.google.com/file/d/1Tc6ak2j2m1rkY36EtnulokiMcRFf0LU_/view?usp=drivesdk"},{"Khoi":"KHOI 10","Mon":"DIA 10","SBD":"55100129","Ten file":"55100129 - Trần Quang Hiếu.jpg","Link":"https://drive.google.com/file/d/1TohXHo1EMMVmnry9J7oIUzVGHydk31yk/view?usp=drivesdk"},{"Khoi":"KHOI 10","Mon":"DIA 10","SBD":"55100078","Ten file":"55100078 - Hồng Mỹ Diệp.jpg","Link":"https://drive.google.com/file/d/1URPbwUilKg2heJwrsA70iqA9LUEljheR/view?usp=drivesdk"},{"Khoi":"KHOI 10","Mon":"DIA 10","SBD":"55100192","Ten file":"55100192 - Lê Hoàng Lâm.jpg","Link":"https://drive.google.com/file/d/1UhYIZku1eWNO-fl4IkAb8P2e--r389Ht/view?usp=drivesdk"},{"Khoi":"KHOI 10","Mon":"DIA 10","SBD":"55100105","Ten file":"55100105 - Hoàng Ngọc Hà.jpg","Link":"https://drive.google.com/file/d/1X37npH0TUtQWJtFHrGRnq7eEMbLAeJ-Z/view?usp=drivesdk"},{"Khoi":"KHOI 10","Mon":"DIA 10","SBD":"55100143","Ten file":"55100143 - Trương Minh Huy.jpg","Link":"https://drive.google.com/file/d/1XCzZomt3zA4H847v_M8ZaIvN_TGAigdP/view?usp=drivesdk"},{"Khoi":"KHOI 10","Mon":"DIA 10","SBD":"55100160","Ten file":"55100160 - Đỗ Hải Ngân Khánh.jpg","Link":"https://drive.google.com/file/d/1aeT4beM_BjqnlGG7moXnM9b-0l6c5fxY/view?usp=drivesdk"},{"Khoi":"KHOI 10","Mon":"DIA 10","SBD":"55100177","Ten file":"55100177 - Huỳnh Minh Khôi.jpg","Link":"https://drive.google.com/file/d/1br6As5dadUlA2sol7lPvNma64JvDjFIZ/view?usp=drivesdk"},{"Khoi":"KHOI 10","Mon":"DIA 10","SBD":"55100118","Ten file":"55100118 - Nguyễn Gia Hân.jpg","Link":"https://drive.google.com/file/d/1cXwbQYEQTcxBM9XTqG_zW8goLudridQJ/view?usp=drivesdk"},{"Khoi":"KHOI 10","Mon":"DIA 10","SBD":"55100156","Ten file":"55100156 - Trương Minh Vĩnh Khang.jpg","Link":"https://drive.google.com/file/d/1kyts07OY35pZTLVfrcTYB5qpEKph9MLV/view?usp=drivesdk"},{"Khoi":"KHOI 10","Mon":"DIA 10","SBD":"55100087","Ten file":"55100087 - Phạm Minh Duyên.jpg","Link":"https://drive.google.com/file/d/1mCSVyhODeNYOerbam-8I9VVn8W8eQ8IV/view?usp=drivesdk"},{"Khoi":"KHOI 10","Mon":"DIA 10","SBD":"55100193","Ten file":"55100193 - Nguyễn Hoàng Lâm.jpg","Link":"https://drive.google.com/file/d/1mJC3M87igqFpdBviJmkj0XL9ruupJaxs/view?usp=drivesdk"},{"Khoi":"KHOI 10","Mon":"DIA 10","SBD":"55100108","Ten file":"55100108 - Phạm Hải Hà.jpg","Link":"https://drive.google.com/file/d/1u2UlKJqFnDPIFNB64tRwIQR5taVeoIf1/view?usp=drivesdk"},{"Khoi":"KHOI 10","Mon":"DIA 10","SBD":"55100203","Ten file":"55100203 - Nguyễn Hoàng Long.jpg","Link":"https://drive.google.com/file/d/1wGMbmKGFM6ITRIv-70L3rBFxxXgpcP5A/view?usp=drivesdk"},{"Khoi":"KHOI 10","Mon":"DIA 10","SBD":"55100098","Ten file":"55100098 - Trương Minh Đông.jpg","Link":"https://drive.google.com/file/d/1ycUw0mwS0SX0ZqBdJXRNZ9B2xpo68EG5/view?usp=drivesdk"},{"Khoi":"KHOI 10","Mon":"DIA 10","SBD":"55100047","Ten file":"55100047 - Võ Hoàng Lan Anh.jpg","Link":"https://drive.google.com/file/d/10FUiUwwLdpNl3kbm_lN54nED6KvbRGGN/view?usp=drivesdk"},{"Khoi":"KHOI 10","Mon":"DIA 10","SBD":"55100057","Ten file":"55100057 - Tăng Thiên Bảo.jpg","Link":"https://drive.google.com/file/d/14qp4gbqlfDJBBujwffr2U40onOpNDMGW/view?usp=drivesdk"},{"Khoi":"KHOI 10","Mon":"DIA 10","SBD":"55100068","Ten file":"55100068 - Trần Huỳnh Bảo Châu.jpg","Link":"https://drive.google.com/file/d/16TmaUkivxNkvwAg57dGDLhfDUbo3vVG-/view?usp=drivesdk"},{"Khoi":"KHOI 10","Mon":"DIA 10","SBD":"55100077","Ten file":"55100077 - Trần Nguyễn Ngọc Diễm.jpg","Link":"https://drive.google.com/file/d/18DkxQkciVKxN49zYFk2eOp2OE5bXLRZa/view?usp=drivesdk"},{"Khoi":"KHOI 10","Mon":"DIA 10","SBD":"55100033","Ten file":"55100033 - Nguyễn Trần Thùy Anh.jpg","Link":"https://drive.google.com/file/d/1B6dnkda_ngWDC1qUkaPCs9BTz2OvNnhB/view?usp=drivesdk"},{"Khoi":"KHOI 10","Mon":"DIA 10","SBD":"55100019","Ten file":"55100019 - Lê Hồng Anh.jpg","Link":"https://drive.google.com/file/d/1EAx00lH0L-Ylb2Wy3-oGBXjsk6EWpkIV/view?usp=drivesdk"},{"Khoi":"KHOI 10","Mon":"DIA 10","SBD":"55100030","Ten file":"55100030 - Nguyễn Phan Trâm Anh.jpg","Link":"https://drive.google.com/file/d/1GCz5td8md_rxOYvQQctDYfRfrfM0wsK3/view?usp=drivesdk"},{"Khoi":"KHOI 10","Mon":"DIA 10","SBD":"55100018","Ten file":"55100018 - Lê Gia Phương Anh.jpg","Link":"https://drive.google.com/file/d/1KMN--sK68Yb91CKIZ55AE0ljUlWaYkzR/view?usp=drivesdk"},{"Khoi":"KHOI 10","Mon":"DIA 10","SBD":"55100050","Ten file":"55100050 - Vũ Hoàng Phương Anh.jpg","Link":"https://drive.google.com/file/d/1Ly-Em7LsxeTeiFWOzaxGtkg4RdOp3n4m/view?usp=drivesdk"},{"Khoi":"KHOI 10","Mon":"DIA 10","SBD":"55100065","Ten file":"55100065 - Lê Hoàng Minh Châu.jpg","Link":"https://drive.google.com/file/d/1MvLD-oakNKPUIG7zbJJMQF7y8SWZKmjc/view?usp=drivesdk"},{"Khoi":"KHOI 10","Mon":"DIA 10","SBD":"55100042","Ten file":"55100042 - Trần Ngọc Hải Anh.jpg","Link":"https://drive.google.com/file/d/1R3FA382lObGsBkCHs2HErHx87O7puZFU/view?usp=drivesdk"},{"Khoi":"KHOI 10","Mon":"DIA 10","SBD":"55100069","Ten file":"55100069 - Hiệp Uyển Chi.jpg","Link":"https://drive.google.com/file/d/1Sy7jVkAJ-6130qZzo84dJI4LHV88dkqm/view?usp=drivesdk"},{"Khoi":"KHOI 10","Mon":"DIA 10","SBD":"55100062","Ten file":"55100062 - Diệp Minh Châu.jpg","Link":"https://drive.google.com/file/d/1Utz2h49P0-kYfivEMzj7T-_If1q__bHQ/view?usp=drivesdk"},{"Khoi":"KHOI 10","Mon":"DIA 10","SBD":"55100038","Ten file":"55100038 - Phan Minh Anh.jpg","Link":"https://drive.google.com/file/d/1WuYY5fV4rYsd3iMuTTig4Luucw4RA2rH/view?usp=drivesdk"},{"Khoi":"KHOI 10","Mon":"DIA 10","SBD":"55100012","Ten file":"55100012 - Châu Quốc Anh.jpg","Link":"https://drive.google.com/file/d/1YEXWyH13xBGAXGZplaC7hib4xpeWkwr6/view?usp=drivesdk"},{"Khoi":"KHOI 10","Mon":"DIA 10","SBD":"55100031","Ten file":"55100031 - Nguyễn Phúc Anh.jpg","Link":"https://drive.google.com/file/d/1a4A4QjVhtwXAAH6XDdgx_ccwgUSxS1lO/view?usp=drivesdk"},{"Khoi":"KHOI 10","Mon":"DIA 10","SBD":"55100023","Ten file":"55100023 - Nguyễn Đoàn Trâm Anh.jpg","Link":"https://drive.google.com/file/d/1buW-BsO_WOLajT4IwxOi5R9yzqSPLwpY/view?usp=drivesdk"},{"Khoi":"KHOI 10","Mon":"DIA 10","SBD":"55100005","Ten file":"55100005 - Nguyễn Gia An.jpg","Link":"https://drive.google.com/file/d/1cFGbQec8spakOTckgtQ13rOM4AU7M3E5/view?usp=drivesdk"},{"Khoi":"KHOI 10","Mon":"DIA 10","SBD":"55100075","Ten file":"55100075 - Phùng Khả Di.jpg","Link":"https://drive.google.com/file/d/1eNe5kqtpuDBakUcWFHR9XxDYlv3EJtnw/view?usp=drivesdk"},{"Khoi":"KHOI 10","Mon":"DIA 10","SBD":"55100072","Ten file":"55100072 - Huỳnh Anh Duy Chương.jpg","Link":"https://drive.google.com/file/d/1h61-_CysJYvG8VAV4-mpaUcXOcfA3Bdr/view?usp=drivesdk"},{"Khoi":"KHOI 10","Mon":"DIA 10","SBD":"55100044","Ten file":"55100044 - Trần Quỳnh Anh.jpg","Link":"https://drive.google.com/file/d/1kvB4VsFfcqdErs5lolL72wOqtIpZP9xE/view?usp=drivesdk"},{"Khoi":"KHOI 10","Mon":"DIA 10","SBD":"55100029","Ten file":"55100029 - Nguyễn Ngọc Vân Anh.jpg","Link":"https://drive.google.com/file/d/1nNm49f_8CIjt59aTvDpRIWRmZVEKZTJD/view?usp=drivesdk"},{"Khoi":"KHOI 10","Mon":"DIA 10","SBD":"55100036","Ten file":"55100036 - Phạm Lan Anh.jpg","Link":"https://drive.google.com/file/d/1o7ylxUSNX0yxLyaXaFDSVWXxn4Lhbvpw/view?usp=drivesdk"},{"Khoi":"KHOI 10","Mon":"DIA 10","SBD":"55100035","Ten file":"55100035 - Nguyễn Võ Quốc Anh.jpg","Link":"https://drive.google.com/file/d/1p61p0iYR5HJOjCSMGw8gAJrwyifRh1hx/view?usp=drivesdk"},{"Khoi":"KHOI 10","Mon":"DIA 10","SBD":"55100009","Ten file":"55100009 - Bùi Kim Anh.jpg","Link":"https://drive.google.com/file/d/1pC2vs6Hy0VRWJDPaOBSI3N11kl9ShQpw/view?usp=drivesdk"},{"Khoi":"KHOI 10","Mon":"DIA 10","SBD":"55100025","Ten file":"55100025 - Nguyễn Ngọc Anh.jpg","Link":"https://drive.google.com/file/d/1qyfuJ3bZoQwogvviLXvd0-p2z5b37QU6/view?usp=drivesdk"},{"Khoi":"KHOI 10","Mon":"DIA 10","SBD":"55100022","Ten file":"55100022 - Lê Trúc Anh.jpg","Link":"https://drive.google.com/file/d/1v73sa9iORDKKUTechy1Pp6FDh-Q8oqZn/view?usp=drivesdk"},{"Khoi":"KHOI 10","Mon":"DIA 10","SBD":"55100039","Ten file":"55100039 - Phan Phương Anh.jpg","Link":"https://drive.google.com/file/d/1yYhhavJofp8UYmQKIcKH28tfAQTpM2YR/view?usp=drivesdk"}]